llama_index/vector_stores/astra/__init__.py
llama_index/vector_stores/astra/base.py
llama_index_vector_stores_astra-0.1.2.dist-info/METADATA
llama_index_vector_stores_astra-0.1.2.dist-info/WHEEL
llama_index_vector_stores_astra-0.1.2.dist-info/RECORD
