Metadata-Version: 2.1
Name: llama-index-vector-stores-astra
Version: 0.1.2
Summary: llama-index vector_stores astra integration
License: MIT
Author: Your Name
Author-email: you@example.com
Requires-Python: >=3.8.1,<4.0
Classifier: License :: OSI Approved :: MIT License
Classifier: Programming Language :: Python :: 3
Classifier: Programming Language :: Python :: 3.9
Classifier: Programming Language :: Python :: 3.10
Classifier: Programming Language :: Python :: 3.11
Classifier: Programming Language :: Python :: 3.12
Requires-Dist: astrapy (>=0.7.1,<0.8.0)
Requires-Dist: llama-index-core (>=0.10.1,<0.11.0)
